exonware/__init__.py
exonware/xwquery/__init__.py
exonware/xwquery/version.py
exonware/xwquery/executors/__init__.py
exonware/xwquery/executors/base.py
exonware/xwquery/executors/capability_checker.py
exonware/xwquery/executors/contracts.py
exonware/xwquery/executors/defs.py
exonware/xwquery/executors/engine.py
exonware/xwquery/executors/errors.py
exonware/xwquery/executors/registry.py
exonware/xwquery/executors/advanced/__init__.py
exonware/xwquery/executors/advanced/aggregate_executor.py
exonware/xwquery/executors/advanced/ask_executor.py
exonware/xwquery/executors/advanced/construct_executor.py
exonware/xwquery/executors/advanced/describe_executor.py
exonware/xwquery/executors/advanced/for_loop_executor.py
exonware/xwquery/executors/advanced/foreach_executor.py
exonware/xwquery/executors/advanced/join_executor.py
exonware/xwquery/executors/advanced/let_executor.py
exonware/xwquery/executors/advanced/mutation_executor.py
exonware/xwquery/executors/advanced/options_executor.py
exonware/xwquery/executors/advanced/pipe_executor.py
exonware/xwquery/executors/advanced/subscribe_executor.py
exonware/xwquery/executors/advanced/subscription_executor.py
exonware/xwquery/executors/advanced/union_executor.py
exonware/xwquery/executors/advanced/window_executor.py
exonware/xwquery/executors/advanced/with_cte_executor.py
exonware/xwquery/executors/aggregation/__init__.py
exonware/xwquery/executors/aggregation/avg_executor.py
exonware/xwquery/executors/aggregation/count_executor.py
exonware/xwquery/executors/aggregation/distinct_executor.py
exonware/xwquery/executors/aggregation/group_executor.py
exonware/xwquery/executors/aggregation/having_executor.py
exonware/xwquery/executors/aggregation/max_executor.py
exonware/xwquery/executors/aggregation/min_executor.py
exonware/xwquery/executors/aggregation/sum_executor.py
exonware/xwquery/executors/aggregation/summarize_executor.py
exonware/xwquery/executors/array/__init__.py
exonware/xwquery/executors/array/indexing_executor.py
exonware_xwquery-0.0.1.4.dist-info/METADATA
exonware_xwquery-0.0.1.4.dist-info/WHEEL
exonware_xwquery-0.0.1.4.dist-info/licenses/LICENSE
exonware_xwquery-0.0.1.4.dist-info/RECORD
