Metadata-Version: 2.4
Name: exonware-xwquery
Version: 0.0.1.4
Summary: Universal query language for data structures - 50+ operations, 35+ format converters
Project-URL: Homepage, https://exonware.com
Project-URL: Repository, https://github.com/exonware/xwquery
Project-URL: Documentation, https://github.com/exonware/xwquery#readme
Author-email: "Eng. Muhammad AlShehri" <connect@exonware.com>
License: MIT
License-File: LICENSE
Keywords: conversion,cypher,data,exonware,graphql,query,sparql,sql
Classifier: Development Status :: 3 - Alpha
Classifier: Intended Audience :: Developers
Classifier: License :: OSI Approved :: MIT License
Classifier: Operating System :: OS Independent
Classifier: Programming Language :: Python :: 3
Classifier: Programming Language :: Python :: 3.8
Classifier: Programming Language :: Python :: 3.9
Classifier: Programming Language :: Python :: 3.10
Classifier: Programming Language :: Python :: 3.11
Classifier: Programming Language :: Python :: 3.12
Classifier: Topic :: Database :: Database Engines/Servers
Classifier: Topic :: Software Development :: Libraries :: Python Modules
Requires-Python: >=3.8
Requires-Dist: exonware-xwnode
Requires-Dist: exonware-xwsystem
Provides-Extra: dev
Requires-Dist: black>=23.0.0; extra == 'dev'
Requires-Dist: isort>=5.12.0; extra == 'dev'
Requires-Dist: mypy>=1.0.0; extra == 'dev'
Requires-Dist: pytest-asyncio>=0.21.0; extra == 'dev'
Requires-Dist: pytest-cov>=4.0.0; extra == 'dev'
Requires-Dist: pytest>=7.0.0; extra == 'dev'
Provides-Extra: full
Requires-Dist: exonware-xwnode[full]; extra == 'full'
Provides-Extra: lazy
Requires-Dist: exonware-xwnode[lazy]; extra == 'lazy'
